pymech-2.0.1.dist-info/METADATA
pymech-2.0.1.dist-info/WHEEL
pymech-2.0.1.dist-info/entry_points.txt
pymech-2.0.1.dist-info/licenses/LICENSE
pymech/__init__.py
pymech/_version.py
pymech/core.py
pymech/dataset.py
pymech/log.py
pymech/meshtools.py
pymech/neksuite/__init__.py
pymech/neksuite/field.py
pymech/neksuite/map.py
pymech/neksuite/mesh.py
pymech/simsonsuite.py
pymech/vtksuite.py
pymech-2.0.1.dist-info/RECORD
